odoo10_addon_mis_builder_operating_unit-10.0.1.0.0.99.dev7-py2.7-nspkg.pth
odoo/addons/mis_builder_operating_unit/README.rst
odoo/addons/mis_builder_operating_unit/__init__.py
odoo/addons/mis_builder_operating_unit/__manifest__.py
odoo/addons/mis_builder_operating_unit/model/__init__.py
odoo/addons/mis_builder_operating_unit/model/mis_builder.py
odoo/addons/mis_builder_operating_unit/security/mis_builder_security.xml
odoo/addons/mis_builder_operating_unit/static/description/icon.png
odoo/addons/mis_builder_operating_unit/view/mis_builder.xml
odoo10_addon_mis_builder_operating_unit-10.0.1.0.0.99.dev7.dist-info/METADATA
odoo10_addon_mis_builder_operating_unit-10.0.1.0.0.99.dev7.dist-info/RECORD
odoo10_addon_mis_builder_operating_unit-10.0.1.0.0.99.dev7.dist-info/WHEEL
odoo10_addon_mis_builder_operating_unit-10.0.1.0.0.99.dev7.dist-info/namespace_packages.txt
odoo10_addon_mis_builder_operating_unit-10.0.1.0.0.99.dev7.dist-info/top_level.txt
